{
  "schema": "pactum.contract_reviewer_result.v1alpha1",
  "run_id": "run_20260618_054400",
  "attempt_id": "contract_reviewer_attempt_023",
  "reviewer": "codex",
  "lens": "completeness",
  "started_at": "2026-06-18T05:53:53.512024Z",
  "finished_at": "2026-06-18T05:54:12.779378Z",
  "duration_ms": 19267,
  "exit_code": 0,
  "timed_out": false,
  "stdout": "contract/reviewer/attempts/contract_reviewer_attempt_023/stdout.log",
  "stderr": "contract/reviewer/attempts/contract_reviewer_attempt_023/stderr.log"
}
