{
  "schema": "pactum.contract_reviewer_result.v1alpha1",
  "run_id": "run_20260621_144127",
  "attempt_id": "contract_reviewer_attempt_012",
  "reviewer": "codex",
  "lens": "completeness",
  "started_at": "2026-06-21T14:50:00.863309Z",
  "finished_at": "2026-06-21T14:50:38.701086Z",
  "duration_ms": 37837,
  "exit_code": 0,
  "timed_out": false,
  "stdout": "contract/reviewer/attempts/contract_reviewer_attempt_012/stdout.log",
  "stderr": "contract/reviewer/attempts/contract_reviewer_attempt_012/stderr.log"
}
